[
	{
    "idx": 0,
    "scriptType": "text",
    "storyTeller": null,
    "text": "인생 첫 면접, 그리고 인생 첫 탈락.",
    "centerImageUrl": "a",
    "LeftImageUrl2": "a",
    "RightImageUrl3": "a",
    "backgroundImageUrl": "classroom",
    "plusIndex": 1
  },
	{
    "idx": 1,
    "scriptType": "text",
    "storyTeller": "주인공",
    "text": "\"탈락이라. 기분이 좋진 않네.\"",
    "centerImageUrl": "jeonghyun",
    "LeftImageUrl2": "a",
    "RightImageUrl3": "a",
    "backgroundImageUrl": "classroom",
    "plusIndex": 1
  },
	{
    "idx": 2,
    "scriptType": "text",
    "storyTeller": null,
    "text": "탈락 소식을 서봄에게 알릴까 말까 고민하다, 알리지 않기로 한다.",
    "centerImageUrl": "a",
    "LeftImageUrl2": "a",
    "RightImageUrl3": "a",
    "backgroundImageUrl": "classroom",
    "plusIndex": 1
  },
	{
    "idx": 3,
    "scriptType": "text",
    "storyTeller": "주인공",
    "text": "\"그냥 잠이나 자야지.\"",
    "centerImageUrl": "a",
    "LeftImageUrl2": "a",
    "RightImageUrl3": "a",
    "backgroundImageUrl": "classroom",
    "plusIndex": 1
  },
	{
    "idx": 4,
    "scriptType": "text",
    "storyTeller": null,
    "text": "30분쯤 지났을까, 휴대전화가 울리기 시작한다. 화면에 떠있는 두글자, '서봄'",
    "centerImageUrl": "a",
    "LeftImageUrl2": "a",
    "RightImageUrl3": "a",
    "backgroundImageUrl": "classroom",
    "plusIndex": 1
  },
	{
    "idx": 5,
    "scriptType": "text",
    "storyTeller": null,
    "text": "받을까 말까 고민하다, 받기로 한다.",
    "centerImageUrl": "a",
    "LeftImageUrl2": "a",
    "RightImageUrl3": "a",
    "backgroundImageUrl": "classroom",
    "plusIndex": 1
  },
	{
    "idx": 6,
    "scriptType": "text",
    "storyTeller": "주인공",
    "text": "\"여보세요.\"",
    "centerImageUrl": "a",
    "LeftImageUrl2": "a",
    "RightImageUrl3": "a",
    "backgroundImageUrl": "classroom",
    "plusIndex": 1
  },
	{
    "idx": 7,
    "scriptType": "text",
    "storyTeller": "서봄",
    "text": "\"오늘 보미자동차 발표났던데, 어떻게 됐어?\"",
    "centerImageUrl": "a",
    "LeftImageUrl2": "a",
    "RightImageUrl3": "a",
    "backgroundImageUrl": "classroom",
    "plusIndex": 1
  },
	{
    "idx": 8,
    "scriptType": "text",
    "storyTeller": "주인공",
    "text": "\"떨어졌지 뭐. 너는?\"",
    "centerImageUrl": "a",
    "LeftImageUrl2": "a",
    "RightImageUrl3": "a",
    "backgroundImageUrl": "classroom",
    "plusIndex": 1
  },
	{
    "idx": 9,
    "scriptType": "text",
    "storyTeller": "서봄",
    "text": "\"나는 붙었지.\"",
    "centerImageUrl": "a",
    "LeftImageUrl2": "a",
    "RightImageUrl3": "a",
    "backgroundImageUrl": "classroom",
    "plusIndex": 1
  },
	{
    "idx": 10,
    "scriptType": "text",
    "storyTeller": "주인공",
    "text": "\"역시 서봄이네. 나같은거랑은 비교도 안된달까..\"",
    "centerImageUrl": "a",
    "LeftImageUrl2": "a",
    "RightImageUrl3": "a",
    "backgroundImageUrl": "classroom",
    "plusIndex": 1
  },
	{
    "idx": 11,
    "scriptType": "text",
    "storyTeller": "서봄",
    "text": "\"그런... 운이 좋았을 뿐이고. 너도 다음번엔 잘 할거야.\"",
    "centerImageUrl": "a",
    "LeftImageUrl2": "a",
    "RightImageUrl3": "a",
    "backgroundImageUrl": "classroom",
    "plusIndex": 1
  },
	{
    "idx": 12,
    "scriptType": "text",
    "storyTeller": "주인공",
    "text": "\"이번에 잘했으면 더 좋았을텐데 말이지.\"",
    "centerImageUrl": "a",
    "LeftImageUrl2": "a",
    "RightImageUrl3": "a",
    "backgroundImageUrl": "classroom",
    "plusIndex": 1
  },
	{
    "idx": 13,
    "scriptType": "text",
    "storyTeller": null,
    "text": "탈락의 슬픔 때문일까, 서봄에게 괜히 퉁명스럽게 말하게 되는 것 같다.",
    "centerImageUrl": "a",
    "LeftImageUrl2": "a",
    "RightImageUrl3": "a",
    "backgroundImageUrl": "classroom",
    "plusIndex": 1
  },
	{
    "idx": 14,
    "scriptType": "text",
    "storyTeller": "주인공",
    "text": "\"더 할 말 없으면 전화 끊을게. 오늘 좀 피곤하네.\"",
    "centerImageUrl": "a",
    "LeftImageUrl2": "a",
    "RightImageUrl3": "a",
    "backgroundImageUrl": "classroom",
    "plusIndex": 1
  },
	{
    "idx": 15,
    "scriptType": "text",
    "storyTeller": "서봄",
    "text": "\"응... 푹 쉬어.\"",
    "centerImageUrl": "a",
    "LeftImageUrl2": "a",
    "RightImageUrl3": "a",
    "backgroundImageUrl": "classroom",
    "plusIndex": 1
  },
	{
    "idx": 16,
    "scriptType": "text",
    "storyTeller": null,
    "text": "서봄과의 전화가 끝난 후 다시 잠에 드는 나.",
    "centerImageUrl": "a",
    "LeftImageUrl2": "a",
    "RightImageUrl3": "a",
    "backgroundImageUrl": "classroom",
    "plusIndex": 1
  },
	{
    "idx": 17,
    "scriptType": "text",
    "storyTeller": null,
    "text": "한 숨 자고 일어나보니 서봄에게서 문자가 한 통 와있다.",
    "centerImageUrl": "a",
    "LeftImageUrl2": "a",
    "RightImageUrl3": "a",
    "backgroundImageUrl": "classroom",
    "plusIndex": 1
  },
	{
    "idx": 18,
    "scriptType": "text",
    "storyTeller": "서봄",
    "text": "\"탈락했다고 너무 상심해있지 말구. 내일 시간 괜찮으면 같이 맛있는거라도 먹으러 갈까?\"",
    "centerImageUrl": "a",
    "LeftImageUrl2": "a",
    "RightImageUrl3": "a",
    "backgroundImageUrl": "classroom",
    "plusIndex": 1
  },
	{
    "idx": 19,
    "scriptType": "text",
    "storyTeller": null,
    "text": "이녀석. 풀이 죽은 나를 위로해주기 위해 나름 노력하고 있는 중인 모양이다. 그럴 필요 없는데... 하여간 너무 착해빠졌다니까, 얘는.",
    "centerImageUrl": "a",
    "LeftImageUrl2": "a",
    "RightImageUrl3": "a",
    "backgroundImageUrl": "classroom",
    "plusIndex": 1
  },
	{
    "idx": 20,
    "scriptType": "text",
    "storyTeller": "주인공",
    "text": "\"뭐, 털고 일어나야지. 탈락이 뭔 대수라고.\"",
    "centerImageUrl": "a",
    "LeftImageUrl2": "a",
    "RightImageUrl3": "a",
    "backgroundImageUrl": "classroom",
    "plusIndex": 1
  },
	{
    "idx": 21,
    "scriptType": "text",
    "storyTeller": null,
    "text": "서봄의 응원에 힘입어 약간 회복을 한 느낌이다.",
    "centerImageUrl": "a",
    "LeftImageUrl2": "a",
    "RightImageUrl3": "a",
    "backgroundImageUrl": "classroom",
    "plusIndex": 1
  },
	{
    "idx": 22,
    "scriptType": "text",
    "storyTeller": "주인공",
    "text": "\"내일 뭐먹을지 고민해봐야 겠네.\"",
    "centerImageUrl": "a",
    "LeftImageUrl2": "a",
    "RightImageUrl3": "a",
    "backgroundImageUrl": "classroom",
    "plusIndex": 1
  },
	{
    "idx": 23,
    "scriptType": "text",
    "storyTeller": null,
    "text": "다음날. 서봄과의 약속 장소.",
    "centerImageUrl": "a",
    "LeftImageUrl2": "a",
    "RightImageUrl3": "a",
    "backgroundImageUrl": "classroom",
    "plusIndex": 1
  },
	{
    "idx": 24,
    "scriptType": "text",
    "storyTeller": "주인공",
    "text": "\"너무 일찍 온건가. 어디, 미리 들어가서 주문을 해두는게 낫겠지?\"",
    "centerImageUrl": "a",
    "LeftImageUrl2": "a",
    "RightImageUrl3": "a",
    "backgroundImageUrl": "classroom",
    "plusIndex": 1
  },
	{
    "idx": 25,
    "scriptType": "text",
    "storyTeller": null,
    "text": "식당에 들어가 미리 주문을 해둔다.",
    "centerImageUrl": "a",
    "LeftImageUrl2": "a",
    "RightImageUrl3": "a",
    "backgroundImageUrl": "classroom",
    "plusIndex": 1
  },
	{
    "idx": 26,
    "scriptType": "text",
    "storyTeller": "주인공",
    "text": "\"여기 곱창 2판이요\"",
    "centerImageUrl": "a",
    "LeftImageUrl2": "a",
    "RightImageUrl3": "a",
    "backgroundImageUrl": "classroom",
    "plusIndex": 1
  },
	{
    "idx": 27,
    "scriptType": "text",
    "storyTeller": null,
    "text": "음식을 적당히 시켜두곤 서봄을 기다린다. 10분쯤 지났을까, 서봄이 도착했다.",
    "centerImageUrl": "a",
    "LeftImageUrl2": "a",
    "RightImageUrl3": "a",
    "backgroundImageUrl": "classroom",
    "plusIndex": 1
  },
	{
    "idx": 28,
    "scriptType": "text",
    "storyTeller": "주인공",
    "text": "\"여, 보미자동차 합격자.\"",
    "centerImageUrl": "a",
    "LeftImageUrl2": "a",
    "RightImageUrl3": "a",
    "backgroundImageUrl": "classroom",
    "plusIndex": 1
  },
	{
    "idx": 29,
    "scriptType": "text",
    "storyTeller": "서봄",
    "text": "\"괜히 민망한걸. 음식은? 시켰어?\"",
    "centerImageUrl": "a",
    "LeftImageUrl2": "a",
    "RightImageUrl3": "a",
    "backgroundImageUrl": "classroom",
    "plusIndex": 1
  },
	{
    "idx": 30,
    "scriptType": "text",
    "storyTeller": "주인공",
    "text": "\"어어 시켜뒀어. 마실것도 시킬까?\"",
    "centerImageUrl": "a",
    "LeftImageUrl2": "a",
    "RightImageUrl3": "a",
    "backgroundImageUrl": "classroom",
    "plusIndex": 1
  },
	{
    "idx": 31,
    "scriptType": "text",
    "storyTeller": "서봄",
    "text": "\"그럼 난 콜라코카 제로로\"",
    "centerImageUrl": "a",
    "LeftImageUrl2": "a",
    "RightImageUrl3": "a",
    "backgroundImageUrl": "classroom",
    "plusIndex": 1
  },
	{
    "idx": 32,
    "scriptType": "text",
    "storyTeller": "주인공",
    "text": "\"나도 같은거로 시켜야겠다.\"",
    "centerImageUrl": "a",
    "LeftImageUrl2": "a",
    "RightImageUrl3": "a",
    "backgroundImageUrl": "classroom",
    "plusIndex": 1
  },
	{
    "idx": 33,
    "scriptType": "text",
    "storyTeller": null,
    "text": "음료를 주문하고 나자 할 말이 없어진 나와 서봄. 어색한 정적이 흐른다.",
    "centerImageUrl": "a",
    "LeftImageUrl2": "a",
    "RightImageUrl3": "a",
    "backgroundImageUrl": "classroom",
    "plusIndex": 1
  },
	{
    "idx": 34,
    "scriptType": "text",
    "storyTeller": "서봄",
    "text": "\"오늘 날씨가 되게 춥네. 이제 확실히 겨울인 느낌이려나?\"",
    "centerImageUrl": "a",
    "LeftImageUrl2": "a",
    "RightImageUrl3": "a",
    "backgroundImageUrl": "classroom",
    "plusIndex": 1
  },
	{
    "idx": 35,
    "scriptType": "text",
    "storyTeller": "주인공",
    "text": "\"그렇네.\"",
    "centerImageUrl": "a",
    "LeftImageUrl2": "a",
    "RightImageUrl3": "a",
    "backgroundImageUrl": "classroom",
    "plusIndex": 1
  },
	{
    "idx": 36,
    "scriptType": "text",
    "storyTeller": "서봄",
    "text": "\"그나저나 곱창 좋아해? 난 사실 몇번 안먹어봤거든.\"",
    "centerImageUrl": "a",
    "LeftImageUrl2": "a",
    "RightImageUrl3": "a",
    "backgroundImageUrl": "classroom",
    "plusIndex": 1
  },
	{
    "idx": 37,
    "scriptType": "text",
    "storyTeller": "주인공",
    "text": "\"뭐, 그럭저럭.\"",
    "centerImageUrl": "a",
    "LeftImageUrl2": "a",
    "RightImageUrl3": "a",
    "backgroundImageUrl": "classroom",
    "plusIndex": 1
  },
	{
    "idx": 38,
    "scriptType": "text",
    "storyTeller": null,
    "text": "대화를 이어나가려는 서봄과, 단답만 내놓는 나.",
    "centerImageUrl": "a",
    "LeftImageUrl2": "a",
    "RightImageUrl3": "a",
    "backgroundImageUrl": "classroom",
    "plusIndex": 1
  },
	{
    "idx": 39,
    "scriptType": "text",
    "storyTeller": null,
    "text": "탈락에 대한 슬픔은 어제 풀어냈지만, 다른 감정이 남아있을줄은 몰랐다.",
    "centerImageUrl": "a",
    "LeftImageUrl2": "a",
    "RightImageUrl3": "a",
    "backgroundImageUrl": "classroom",
    "plusIndex": 1
  },
	{
    "idx": 40,
    "scriptType": "text",
    "storyTeller": null,
    "text": "함께 합격하고 싶었는데 그러지 못한 것에 대한 아쉬움, 그리고 직장인이 될 서봄과 계속해서 취준생 신분일 나 사이의 심적인 '거리감'이 나를 힘들게 하고 있다.",
    "centerImageUrl": "a",
    "LeftImageUrl2": "a",
    "RightImageUrl3": "a",
    "backgroundImageUrl": "classroom",
    "plusIndex": 1
  },
	{
    "idx": 41,
    "scriptType": "text",
    "storyTeller": null,
    "text": "이런 감정따위를 사람들은 자격지심이라고 부른다.",
    "centerImageUrl": "a",
    "LeftImageUrl2": "a",
    "RightImageUrl3": "a",
    "backgroundImageUrl": "classroom",
    "plusIndex": 1
  },
	{
    "idx": 42,
    "scriptType": "text",
    "storyTeller": "주인공",
    "text": "\"뭐... 보미자동차 합격한거 다시 한번 축하해.\"",
    "centerImageUrl": "a",
    "LeftImageUrl2": "a",
    "RightImageUrl3": "a",
    "backgroundImageUrl": "classroom",
    "plusIndex": 1
  },
	{
    "idx": 43,
    "scriptType": "text",
    "storyTeller": null,
    "text": "아무렇지 않은 척을 하기 위해 축하의 메시지를 전달하는 나. 스스로 생각해도 추하다.",
    "centerImageUrl": "a",
    "LeftImageUrl2": "a",
    "RightImageUrl3": "a",
    "backgroundImageUrl": "classroom",
    "plusIndex": 1
  },
	{
    "idx": 44,
    "scriptType": "text",
    "storyTeller": "서봄",
    "text": "\"운이 좋았지 뭐...\"",
    "centerImageUrl": "a",
    "LeftImageUrl2": "a",
    "RightImageUrl3": "a",
    "backgroundImageUrl": "classroom",
    "plusIndex": 1
  },
	{
    "idx": 45,
    "scriptType": "text",
    "storyTeller": null,
    "text": "겸손한 서봄. 그 겸손한 마음이 나를 더 힘들게 한다.",
    "centerImageUrl": "a",
    "LeftImageUrl2": "a",
    "RightImageUrl3": "a",
    "backgroundImageUrl": "classroom",
    "plusIndex": 1
  },
	{
    "idx": 46,
    "scriptType": "text",
    "storyTeller": "주인공",
    "text": "\"나는... 운이 안좋았고?\"",
    "centerImageUrl": "a",
    "LeftImageUrl2": "a",
    "RightImageUrl3": "a",
    "backgroundImageUrl": "classroom",
    "plusIndex": 1
  },
	{
    "idx": 47,
    "scriptType": "text",
    "storyTeller": "서봄",
    "text": "\"응? 아니 그런말이 아니라,\"",
    "centerImageUrl": "a",
    "LeftImageUrl2": "a",
    "RightImageUrl3": "a",
    "backgroundImageUrl": "classroom",
    "plusIndex": 1
  },
	{
    "idx": 48,
    "scriptType": "text",
    "storyTeller": "주인공",
    "text": "\"아, 부족한건 운이 아니라 실력이었나?\"",
    "centerImageUrl": "a",
    "LeftImageUrl2": "a",
    "RightImageUrl3": "a",
    "backgroundImageUrl": "classroom",
    "plusIndex": 1
  },
	{
    "idx": 49,
    "scriptType": "text",
    "storyTeller": "서봄",
    "text": "\"아니, 그렇지 않아. 분명 다음번엔 잘 될거야.\"",
    "centerImageUrl": "a",
    "LeftImageUrl2": "a",
    "RightImageUrl3": "a",
    "backgroundImageUrl": "classroom",
    "plusIndex": 1
  },
	{
    "idx": 50,
    "scriptType": "text",
    "storyTeller": null,
    "text": "인자한 미소를 지으며 나를 달래주는 서봄. 뭔가 평소와는 다른 느낌이다.",
    "centerImageUrl": "a",
    "LeftImageUrl2": "a",
    "RightImageUrl3": "a",
    "backgroundImageUrl": "classroom",
    "plusIndex": 1
  },
	{
    "idx": 51,
    "scriptType": "text",
    "storyTeller": "주인공",
    "text": "\"너도 하고싶은 말 있으면 솔직히 하라고. 괜히 기분 맞춰준다고 부드럽게 얘기해줄 필요 없으니까.\"",
    "centerImageUrl": "a",
    "LeftImageUrl2": "a",
    "RightImageUrl3": "a",
    "backgroundImageUrl": "classroom",
    "plusIndex": 1
  },
	{
    "idx": 52,
    "scriptType": "text",
    "storyTeller": "서봄",
    "text": "\"난... 진심으로 우리가 같이 합격하길 바랬어.\"",
    "centerImageUrl": "a",
    "LeftImageUrl2": "a",
    "RightImageUrl3": "a",
    "backgroundImageUrl": "classroom",
    "plusIndex": 1
  },
	{
    "idx": 53,
    "scriptType": "text",
    "storyTeller": "주인공",
    "text": "\"어째서?\"",
    "centerImageUrl": "a",
    "LeftImageUrl2": "a",
    "RightImageUrl3": "a",
    "backgroundImageUrl": "classroom",
    "plusIndex": 1
  },
	{
    "idx": 54,
    "scriptType": "text",
    "storyTeller": "서봄",
    "text": "\"그야... 지난 1년동안 열심히 하는걸 누구보다 가까이서 지켜봐왔으니까.\"",
    "centerImageUrl": "a",
    "LeftImageUrl2": "a",
    "RightImageUrl3": "a",
    "backgroundImageUrl": "classroom",
    "plusIndex": 1
  },
	{
    "idx": 55,
    "scriptType": "text",
    "storyTeller": "서봄",
    "text": "\"내가 봐온 너는, 겨우 이런 고난에서 무너질 사람이 아니야.\"",
    "centerImageUrl": "a",
    "LeftImageUrl2": "a",
    "RightImageUrl3": "a",
    "backgroundImageUrl": "classroom",
    "plusIndex": 1
  },
	{
    "idx": 56,
    "scriptType": "text",
    "storyTeller": null,
    "text": "신념에 찬 표정으로 나를 바라보는 서봄.",
    "centerImageUrl": "a",
    "LeftImageUrl2": "a",
    "RightImageUrl3": "a",
    "backgroundImageUrl": "classroom",
    "plusIndex": 1
  },
	{
    "idx": 57,
    "scriptType": "text",
    "storyTeller": null,
    "text": "나조차 나를 믿지 못하고 있던 순간이었다. 그런 순간마저도 서봄은, 내 가능성을 보며 응원하고 있었던 것이다.",
    "centerImageUrl": "a",
    "LeftImageUrl2": "a",
    "RightImageUrl3": "a",
    "backgroundImageUrl": "classroom",
    "plusIndex": 1
  },
	{
    "idx": 58,
    "scriptType": "text",
    "storyTeller": null,
    "text": "순간 울컥한 나는, 급히 고개를 들어 눈물을 삼킨다.",
    "centerImageUrl": "a",
    "LeftImageUrl2": "a",
    "RightImageUrl3": "a",
    "backgroundImageUrl": "classroom",
    "plusIndex": 1
  },
	{
    "idx": 59,
    "scriptType": "text",
    "storyTeller": "주인공",
    "text": "\"서봄.\"",
    "centerImageUrl": "a",
    "LeftImageUrl2": "a",
    "RightImageUrl3": "a",
    "backgroundImageUrl": "classroom",
    "plusIndex": 1
  },
	{
    "idx": 60,
    "scriptType": "text",
    "storyTeller": "서봄",
    "text": "\"응?\"",
    "centerImageUrl": "a",
    "LeftImageUrl2": "a",
    "RightImageUrl3": "a",
    "backgroundImageUrl": "classroom",
    "plusIndex": 1
  },
	{
    "idx": 61,
    "scriptType": "text",
    "storyTeller": "주인공",
    "text": "\"고맙다. 힘이 되네.\"",
    "centerImageUrl": "a",
    "LeftImageUrl2": "a",
    "RightImageUrl3": "a",
    "backgroundImageUrl": "classroom",
    "plusIndex": 1
  },
	{
    "idx": 62,
    "scriptType": "text",
    "storyTeller": "서봄",
    "text": "\"난 진심을 말했을 뿐이야.\"",
    "centerImageUrl": "a",
    "LeftImageUrl2": "a",
    "RightImageUrl3": "a",
    "backgroundImageUrl": "classroom",
    "plusIndex": 1
  },
	{
    "idx": 63,
    "scriptType": "text",
    "storyTeller": "주인공",
    "text": "\"진심인걸 아니까 힘이 나는거야.\"",
    "centerImageUrl": "a",
    "LeftImageUrl2": "a",
    "RightImageUrl3": "a",
    "backgroundImageUrl": "classroom",
    "plusIndex": 1
  },
	{
    "idx": 64,
    "scriptType": "text",
    "storyTeller": null,
    "text": "살짝 미소짓는 서봄. 가슴이 뛴다.",
    "centerImageUrl": "a",
    "LeftImageUrl2": "a",
    "RightImageUrl3": "a",
    "backgroundImageUrl": "classroom",
    "plusIndex": 1
  },
	{
    "idx": 65,
    "scriptType": "text",
    "storyTeller": "주인공",
    "text": "\"저,, 있잖아\"",
    "centerImageUrl": "a",
    "LeftImageUrl2": "a",
    "RightImageUrl3": "a",
    "backgroundImageUrl": "classroom",
    "plusIndex": 1
  },
	{
    "idx": 66,
    "scriptType": "text",
    "storyTeller": "서봄",
    "text": "\"그 전에 부탁 하나만 해도 될까? 응원해준 대가로.\"",
    "centerImageUrl": "a",
    "LeftImageUrl2": "a",
    "RightImageUrl3": "a",
    "backgroundImageUrl": "classroom",
    "plusIndex": 1
  },
	{
    "idx": 67,
    "scriptType": "text",
    "storyTeller": "주인공",
    "text": "\"응? 뭔데?\"",
    "centerImageUrl": "a",
    "LeftImageUrl2": "a",
    "RightImageUrl3": "a",
    "backgroundImageUrl": "classroom",
    "plusIndex": 1
  },
	{
    "idx": 68,
    "scriptType": "text",
    "storyTeller": "서봄",
    "text": "\"사실 오늘 다른 한분도 같이 모이기로 했거든! 이번에 보미자동차 합격하신 분인데, 지금 여기로 오신다네. 괜찮을까?\"",
    "centerImageUrl": "a",
    "LeftImageUrl2": "a",
    "RightImageUrl3": "a",
    "backgroundImageUrl": "classroom",
    "plusIndex": 1
  },
	{
    "idx": 69,
    "scriptType": "text",
    "storyTeller": "주인공",
    "text": "\"어,, 뭐 상관없어. 그래서 내가 도와줄 일이라는게 뭐야?\"",
    "centerImageUrl": "a",
    "LeftImageUrl2": "a",
    "RightImageUrl3": "a",
    "backgroundImageUrl": "classroom",
    "plusIndex": 1
  },
	{
    "idx": 70,
    "scriptType": "text",
    "storyTeller": "서봄",
    "text": "\"별건 아니고, 자리 좀 빨리 비켜주면 안될까 싶어서... 안될까? 저녁값은 내가 계산할게.\"",
    "centerImageUrl": "a",
    "LeftImageUrl2": "a",
    "RightImageUrl3": "a",
    "backgroundImageUrl": "classroom",
    "plusIndex": 1
  },
	{
    "idx": 71,
    "scriptType": "text",
    "storyTeller": "주인공",
    "text": "\"자리? 기왕 먹는거 같이 먹는게 낫지 않아?\"",
    "centerImageUrl": "a",
    "LeftImageUrl2": "a",
    "RightImageUrl3": "a",
    "backgroundImageUrl": "classroom",
    "plusIndex": 1
  },
	{
    "idx": 72,
    "scriptType": "text",
    "storyTeller": "서봄",
    "text": "\"아니 뭐.. 둘이서만 할 얘기도 있고...\"",
    "centerImageUrl": "a",
    "LeftImageUrl2": "a",
    "RightImageUrl3": "a",
    "backgroundImageUrl": "classroom",
    "plusIndex": 1
  },
	{
    "idx": 73,
    "scriptType": "text",
    "storyTeller": null,
    "text": "얼굴이 붉어지는 서봄. 그 때 등 뒤에서 들리는 나이스한 중저음의 목소리.",
    "centerImageUrl": "a",
    "LeftImageUrl2": "a",
    "RightImageUrl3": "a",
    "backgroundImageUrl": "classroom",
    "plusIndex": 1
  },
	{
    "idx": 74,
    "scriptType": "text",
    "storyTeller": "박정현",
    "text": "\"서봄님 안녕하세요. 옆에 계신 분이 그 분인가요?\"",
    "centerImageUrl": "a",
    "LeftImageUrl2": "a",
    "RightImageUrl3": "a",
    "backgroundImageUrl": "classroom",
    "plusIndex": 1
  },
	{
    "idx": 75,
    "scriptType": "text",
    "storyTeller": "서봄",
    "text": "\"네네, 얘가 오늘 보미자동차 떨어진 앤데, 정현님한테 면접 팁같은거 물어보고 싶다고 해서 불러왔어요.\"",
    "centerImageUrl": "a",
    "LeftImageUrl2": "a",
    "RightImageUrl3": "a",
    "backgroundImageUrl": "classroom",
    "plusIndex": 1
  },
	{
    "idx": 76,
    "scriptType": "text",
    "storyTeller": null,
    "text": "순간 머리가 띵해진다. 상황이 정리가 안된다.",
    "centerImageUrl": "a",
    "LeftImageUrl2": "a",
    "RightImageUrl3": "a",
    "backgroundImageUrl": "classroom",
    "plusIndex": 1
  },
	{
    "idx": 77,
    "scriptType": "text",
    "storyTeller": "주인공",
    "text": "\"어,, 이게 지금 무슨 상황인거야?\"",
    "centerImageUrl": "a",
    "LeftImageUrl2": "a",
    "RightImageUrl3": "a",
    "backgroundImageUrl": "classroom",
    "plusIndex": 1
  },
	{
    "idx": 78,
    "scriptType": "text",
    "storyTeller": "서봄",
    "text": "\"무슨 상황이냐니? 네가 정현님 만나서 같이 얘기해보고 싶다고 하지 않았어?\"",
    "centerImageUrl": "a",
    "LeftImageUrl2": "a",
    "RightImageUrl3": "a",
    "backgroundImageUrl": "classroom",
    "plusIndex": 1
  },
	{
    "idx": 79,
    "scriptType": "text",
    "storyTeller": null,
    "text": "한쪽눈을 미친듯이 감으며 '이번 한번만 도와줘' 같은 신호를 보내는 서봄. 아, 그런건가.",
    "centerImageUrl": "a",
    "LeftImageUrl2": "a",
    "RightImageUrl3": "a",
    "backgroundImageUrl": "classroom",
    "plusIndex": 1
  },
	{
    "idx": 80,
    "scriptType": "text",
    "storyTeller": null,
    "text": "서봄은 저 나이스한 박정현이라는 사람과의 자리를 만들기 위해 '불쌍하고 안타까운 탈락자인 나'를 이용한 것이다.",
    "centerImageUrl": "a",
    "LeftImageUrl2": "a",
    "RightImageUrl3": "a",
    "backgroundImageUrl": "classroom",
    "plusIndex": 1
  },
	{
    "idx": 81,
    "scriptType": "text",
    "storyTeller": null,
    "text": "머리를 망치로 얻어맞은 기분이다.",
    "centerImageUrl": "a",
    "LeftImageUrl2": "a",
    "RightImageUrl3": "a",
    "backgroundImageUrl": "classroom",
    "plusIndex": 1
  },
	{
    "idx": 82,
    "scriptType": "text",
    "storyTeller": "주인공",
    "text": "\"아,, 정현님 안녕하세요. 그...\"",
    "centerImageUrl": "a",
    "LeftImageUrl2": "a",
    "RightImageUrl3": "a",
    "backgroundImageUrl": "classroom",
    "plusIndex": 1
  },
	{
    "idx": 83,
    "scriptType": "text",
    "storyTeller": "서봄",
    "text": "\"(알아서 빠지라는 표정)\"",
    "centerImageUrl": "a",
    "LeftImageUrl2": "a",
    "RightImageUrl3": "a",
    "backgroundImageUrl": "classroom",
    "plusIndex": 1
  },
	{
    "idx": 84,
    "scriptType": "text",
    "storyTeller": "주인공",
    "text": "\"죄송해요. 오늘따라 소화가 안돼서, 다음번에 뵈어도 괜찮을까요?\"",
    "centerImageUrl": "a",
    "LeftImageUrl2": "a",
    "RightImageUrl3": "a",
    "backgroundImageUrl": "classroom",
    "plusIndex": 1
  },
	{
    "idx": 85,
    "scriptType": "text",
    "storyTeller": "박정현",
    "text": "\"물론이죠. 무리하지 말아주세요.\"",
    "centerImageUrl": "a",
    "LeftImageUrl2": "a",
    "RightImageUrl3": "a",
    "backgroundImageUrl": "classroom",
    "plusIndex": 1
  },
	{
    "idx": 86,
    "scriptType": "text",
    "storyTeller": "주인공",
    "text": "\"네.. 그럼 이만 가보겠습니다.\"",
    "centerImageUrl": "a",
    "LeftImageUrl2": "a",
    "RightImageUrl3": "a",
    "backgroundImageUrl": "classroom",
    "plusIndex": 1
  },
	{
    "idx": 87,
    "scriptType": "text",
    "storyTeller": "서봄",
    "text": "\"벌써 가게? 아쉽네~\"",
    "centerImageUrl": "a",
    "LeftImageUrl2": "a",
    "RightImageUrl3": "a",
    "backgroundImageUrl": "classroom",
    "plusIndex": 1
  },
	{
    "idx": 88,
    "scriptType": "text",
    "storyTeller": null,
    "text": "신나하는 서봄.",
    "centerImageUrl": "a",
    "LeftImageUrl2": "a",
    "RightImageUrl3": "a",
    "backgroundImageUrl": "classroom",
    "plusIndex": 1
  },
	{
    "idx": 89,
    "scriptType": "text",
    "storyTeller": null,
    "text": "식당을 나와 집으로 돌아가는 길. 갑자기 비가 내리기 시작한다.",
    "centerImageUrl": "a",
    "LeftImageUrl2": "a",
    "RightImageUrl3": "a",
    "backgroundImageUrl": "classroom",
    "plusIndex": 1
  },
	{
    "idx": 90,
    "scriptType": "text",
    "storyTeller": null,
    "text": "오늘 하루만에 많은 것을 잃어버린 느낌이다. 인생의 패배자가 된 기분이다.",
    "centerImageUrl": "a",
    "LeftImageUrl2": "a",
    "RightImageUrl3": "a",
    "backgroundImageUrl": "classroom",
    "plusIndex": 1
  },
	{
    "idx": 91,
    "scriptType": "text",
    "storyTeller": null,
    "text": "거리의 행복해보이는 사람들. 그 속의 나.",
    "centerImageUrl": "a",
    "LeftImageUrl2": "a",
    "RightImageUrl3": "a",
    "backgroundImageUrl": "classroom",
    "plusIndex": 1
  },
	{
    "idx": 92,
    "scriptType": "text",
    "storyTeller": null,
    "text": "억지미소를 지어보려 하지만, 잘 되지 않는다.",
    "centerImageUrl": "a",
    "LeftImageUrl2": "a",
    "RightImageUrl3": "a",
    "backgroundImageUrl": "classroom",
    "plusIndex": 1
  },
	{
    "idx": 93,
    "scriptType": "text",
    "storyTeller": "주인공",
    "text": "\"가슴이... 너무 답답해.\"",
    "centerImageUrl": "a",
    "LeftImageUrl2": "a",
    "RightImageUrl3": "a",
    "backgroundImageUrl": "classroom",
    "plusIndex": 1
  },
	{
    "idx": 94,
    "scriptType": "text",
    "storyTeller": null,
    "text": "어디론가 떠나고 싶다. 아는 사람이 아무도 없는 곳으로.",
    "centerImageUrl": "a",
    "LeftImageUrl2": "a",
    "RightImageUrl3": "a",
    "backgroundImageUrl": "classroom",
    "plusIndex": 1
  },
	{
    "idx": 95,
    "scriptType": "text",
    "storyTeller": "주인공",
    "text": "\"으, 으아, 으아아, 으으으으아아아아!\"",
    "centerImageUrl": "a",
    "LeftImageUrl2": "a",
    "RightImageUrl3": "a",
    "backgroundImageUrl": "classroom",
    "plusIndex": 1
  },
	{
    "idx": 96,
    "scriptType": "text",
    "storyTeller": null,
    "text": "정신을 차려보니, 괴성을 지르며 차도 한복판을 달리고 있는 내가 있다.",
    "centerImageUrl": "a",
    "LeftImageUrl2": "a",
    "RightImageUrl3": "a",
    "backgroundImageUrl": "classroom",
    "plusIndex": 1
  },
	{
    "idx": 97,
    "scriptType": "text",
    "storyTeller": "주인공",
    "text": "\"으, 으아, 으아아!\"",
    "centerImageUrl": "a",
    "LeftImageUrl2": "a",
    "RightImageUrl3": "a",
    "backgroundImageUrl": "classroom",
    "plusIndex": 1
  },
	{
    "idx": 98,
    "scriptType": "text",
    "storyTeller": null,
    "text": "달리는걸 멈출 수 없다. 이렇게라도 하지 않으면, 정신이 버틸 수 없을 것 같다.",
    "centerImageUrl": "a",
    "LeftImageUrl2": "a",
    "RightImageUrl3": "a",
    "backgroundImageUrl": "classroom",
    "plusIndex": 1
  },
	{
    "idx": 99,
    "scriptType": "text",
    "storyTeller": null,
    "text": "사방에서 들려오는 경찰차소리. 지금 이 순간만큼은 경찰이라도 나를 막을 수 없다.",
    "centerImageUrl": "a",
    "LeftImageUrl2": "a",
    "RightImageUrl3": "a",
    "backgroundImageUrl": "classroom",
    "plusIndex": 1
  },
	{
    "idx": 100,
    "scriptType": "text",
    "storyTeller": "경찰",
    "text": "\"거 위험하니까 빨리 인도로 가세요! 젊은 양반이 지금 뭐하고 있는거람.\"",
    "centerImageUrl": "a",
    "LeftImageUrl2": "a",
    "RightImageUrl3": "a",
    "backgroundImageUrl": "classroom",
    "plusIndex": 1
  },
	{
    "idx": 101,
    "scriptType": "text",
    "storyTeller": "주인공",
    "text": "\"죄송합니다.\"",
    "centerImageUrl": "a",
    "LeftImageUrl2": "a",
    "RightImageUrl3": "a",
    "backgroundImageUrl": "classroom",
    "plusIndex": 1
  },
  {
    "idx": 102,
    "scriptType": "changeScript",
    "storyTeller": null,
    "text": "서봄 story -end-.",
    "centerImageUrl": "a",
    "LeftImageUrl2": "a",
    "RightImageUrl3": "a",
    "backgroundImageUrl": "fin",
    "nextScript": "script5",
    "whichSelfStudy": "cs",
    "selfStudyRequired": {"cs": 0},
    "getAlbumNum": 33,
    "plusIndex": 1
  }
]